lipidoz/__init__.py
lipidoz/_pyliquid.py
lipidoz/_uimf.py
lipidoz/_util.py
lipidoz/isotope_scoring.py
lipidoz/workflows.py
lipidoz/gui/__init__.py
lipidoz/gui/__main__.py
lipidoz/gui/_config.py
lipidoz/gui/app.py
lipidoz/gui/processing_window.py
lipidoz/gui/results_window.py
lipidoz/gui/setup_window.py
lipidoz/ml/__init__.py
lipidoz/ml/data.py
lipidoz/ml/view.py
lipidoz/ml/models/__init__.py
lipidoz/ml/models/resnet18.py
lipidoz-1.3.0.dist-info/METADATA
lipidoz-1.3.0.dist-info/WHEEL
lipidoz-1.3.0.dist-info/top_level.txt
lipidoz-1.3.0.dist-info/RECORD
