Metadata-Version: 2.2
Name: lipidoz
Version: 1.3.0
Summary: Python utility for determination of lipid double bond position location from OzID data
Home-page: https://github.com/PNNL-m-q/lipidoz
Author: Dylan Ross
Author-email: dylan.ross@pnnl.gov
Project-URL: Bug Tracker, https://github.com/PNNL-m-q/lipidoz/issues
Classifier: Programming Language :: Python :: 3
Classifier: License :: OSI Approved :: BSD License
Classifier: Operating System :: OS Independent
Requires-Python: >=3.12
Requires-Dist: mzapy
Requires-Dist: matplotlib
Requires-Dist: numpy
Requires-Dist: scipy
Requires-Dist: xlsxwriter
Requires-Dist: pandas
Requires-Dist: scikit-learn
Requires-Dist: scikit_image
Requires-Dist: torch
Requires-Dist: torchvision
